tango/__init__.py
tango/helper.py
tango/model_parameters.py
tango/objectives.py
tango/runtime.py
tango/SQUFL/__init__.py
tango/SQUFL/instances.py
tango/SQUFL/squfl.py
tango/incumbent_finder/__init__.py
tango/incumbent_finder/cardinality_constraint.py
tango/portfolio_optimization/__init__.py
tango/portfolio_optimization/instances.py
tango/portfolio_optimization/portfolio_optimization.py
tango/solvers/__init__.py
tango/solvers/basic_solver_skeleton.py
tango/solvers/indicator_constraints.py
tango/solvers/oa.py
tango/solvers/oa_solver_skeleton.py
tango/solvers/perspective_solver.py
tango/solvers/problem_data.py
tango/solvers/solver_skeleton.py
tango/solvers/tangent_cut.py
tango/solvers/callbacks/__init__.py
tango/solvers/callbacks/callback.py
tango/solvers/callbacks/fractional_cuts.py
tango/solvers/callbacks/fractional_cuts_utils.py
tango/solvers/callbacks/incumbents.py
tango/solvers/callbacks/lazy_cut_utils.py
tango/solvers/callbacks/lazy_cuts.py
tango/solvers/callbacks/output.py
tango/solvers/relaxation/__init__.py
tango/solvers/relaxation/perspective_relaxation.py
tango/solvers/subsolvers/GurobiQPSolver.py
tango/solvers/subsolvers/__init__.py
tango/tests/__init__.py
tango/tests/or_lib_loader.py
tango/tests/portfolio_optimization_test_instances.py
tango/tests/qpsolver_test_instances.py
tango/tests/squfl_test_instances.py
tango/tests/tangent_cut_test_instances.py
tango/tests/test_helper.py
tango/tests/test_model_parameters.py
tango/tests/test_oa_subsolver.py
tango/tests/test_objectives.py
tango/tests/test_portfolio_instances.py
tango/tests/test_portfolio_optimization.py
tango/tests/test_portfolio_optimization_benchmark.py
tango/tests/test_squfl.py
tango/tests/test_tangent_cut.py
tango/tests/utilities_for_tests.py
tangoa/__init__.py
tangoa/helper.py
tangoa/model_parameters.py
tangoa/objectives.py
tangoa/runtime.py
tangoa/SQUFL/__init__.py
tangoa/SQUFL/instances.py
tangoa/SQUFL/squfl.py
tangoa/incumbent_finder/__init__.py
tangoa-0.1.1.1.dist-info/LICENSE
tangoa-0.1.1.1.dist-info/METADATA
tangoa-0.1.1.1.dist-info/WHEEL
tangoa-0.1.1.1.dist-info/top_level.txt
tangoa-0.1.1.1.dist-info/RECORD
