Metadata-Version: 2.1
Name: tangoa
Version: 0.1.1.1
Summary: Library for solving quadratic programs with indicator constraints.
Home-page: https://gitlab.com/Dnis/tango
Author: Dennis Kreber
Author-email: dnis.kk@gmail.com
License: MIT
Platform: UNKNOWN
Classifier: Programming Language :: Python :: 3
Classifier: License :: OSI Approved :: MIT License
Classifier: Operating System :: OS Independent
Requires-Python: >=3.4
License-File: LICENSE
Requires-Dist: numpy
Requires-Dist: scipy
Requires-Dist: threadpoolctl
